miaospeedlib/__init__.py
miaospeedlib/backend.py
miaospeedlib/types/__init__.py
miaospeedlib/types/base.py
miaospeedlib/types/config.py
miaospeedlib/types/draw.py
miaospeedlib/types/exception.py
miaospeedlib/types/items.py
miaospeedlib/types/manager.py
miaospeedlib/types/miaospeed.py
miaospeedlib/types/rule.py
miaospeedlib/types/task.py
miaospeedlib/types/translation.py
miaospeedlib-0.1.2.dist-info/LICENSE
miaospeedlib-0.1.2.dist-info/METADATA
miaospeedlib-0.1.2.dist-info/WHEEL
miaospeedlib-0.1.2.dist-info/top_level.txt
miaospeedlib-0.1.2.dist-info/RECORD
