Metadata-Version: 2.2
Name: miaospeedlib
Version: 0.1.2
Summary: MiaoSpeed Client Library Implementations for Python.
Home-page: https://github.com/AirportR/miaolib
Author: airportr
Author-email: airportroster@gmail.com
Requires-Python: >=3.9
License-File: LICENSE
Requires-Dist: aiohttp>=3.9.2
Requires-Dist: async_timeout>=4.0.2
Requires-Dist: loguru>=0.6.0
Dynamic: author
Dynamic: author-email
Dynamic: description
Dynamic: description-content-type
Dynamic: home-page
Dynamic: requires-dist
Dynamic: requires-python
Dynamic: summary
